chuk_term/__init__.py
chuk_term/cli.py
chuk_term/ui/__init__.py
chuk_term/ui/banners.py
chuk_term/ui/code.py
chuk_term/ui/formatters.py
chuk_term/ui/output.py
chuk_term/ui/prompts.py
chuk_term/ui/streaming.py
chuk_term/ui/terminal.py
chuk_term/ui/theme.py
chuk_term-0.3.dist-info/METADATA
chuk_term-0.3.dist-info/WHEEL
chuk_term-0.3.dist-info/entry_points.txt
chuk_term-0.3.dist-info/RECORD
